pyxtsoawebservice/__init__.py
pyxtsoawebservice/adicionais.py
pyxtsoawebservice/cheque.py
pyxtsoawebservice/concentre.py
pyxtsoawebservice/consults.py
pyxtsoawebservice/crednet.py
pyxtsoawebservice/erros.py
pyxtsoawebservice/fields.py
pyxtsoawebservice/filters.py
pyxtsoawebservice/fisicalCDC.py
pyxtsoawebservice/legalCDC.py
pyxtsoawebservice/logering.py
pyxtsoawebservice/negativacao.py
pyxtsoawebservice/pefin.py
pyxtsoawebservice/tools.py
pyxtsoawebservice/urls.py
pyxtsoawebservice/xml.py
PyXtSoaWebservice-0.0.6.dist-info/LICENSE.txt
PyXtSoaWebservice-0.0.6.dist-info/METADATA
PyXtSoaWebservice-0.0.6.dist-info/WHEEL
PyXtSoaWebservice-0.0.6.dist-info/top_level.txt
PyXtSoaWebservice-0.0.6.dist-info/RECORD
