Metadata-Version: 2.1
Name: PyXtSoaWebservice
Version: 0.0.6
Summary: PyXtSoaWebservice é uma biblioteca de acesso a API da Serasa, utilizando o distribuidor autorizado SOA Webservices
Home-page: https://bitbucket.org/defendi/pyxtsoawebservice
Author: Alexandre Defendi
Author-email: alexandre_defendi@hotmail.com
License: LGPL-v2.1+
Keywords: serasa,consulta,CPF,CNPJ
Platform: UNKNOWN
Classifier: Environment :: Plugins
Classifier: Intended Audience :: Developers
Classifier: License :: OSI Approved :: GNU Lesser General Public License v2 or later (LGPLv2+)
Classifier: Operating System :: OS Independent
Classifier: Programming Language :: Python :: 3.7
Classifier: Programming Language :: Python :: 3.6
Classifier: Programming Language :: Python :: 3.5
Classifier: Programming Language :: Python :: 3.4
Classifier: Topic :: Software Development :: Libraries :: Python Modules
Requires-Python: >=3.4
Requires-Dist: lxml (<5,>=3.5.0)
Requires-Dist: zeep
